{
    "tags": [
        {
            "name": "hexID",
            "value": "FZPPTV9AX"
        },
        {
            "name": "oompType",
            "value": "FOOTPRINT"
        },
        {
            "name": "oompSize",
            "value": "eagle"
        },
        {
            "name": "oompColor",
            "value": "Pimoroni-Eagle-Library"
        },
        {
            "name": "oompDesc",
            "value": "pimoroni"
        },
        {
            "name": "oompIndex",
            "value": "PTV09A-X"
        },
        {
            "name": "oompName",
            "value": "Pimoroni-Eagle-Library/pimoroni/PTV09A-X"
        },
        {
            "name": "oompID",
            "value": "FOOTPRINT-eagle-Pimoroni-Eagle-Library-pimoroni-PTV09A-X"
        },
        {
            "name": "oompID",
            "value": "FOOTPRINT-eagle-Pimoroni-Eagle-Library-pimoroni-PTV09A-X"
        },
        {
            "name": "name",
            "value": ""
        }
    ]
}