{
    "tags": [
        {
            "name": "hexID",
            "value": "FZECONWAGO233236"
        },
        {
            "name": "oompType",
            "value": "FOOTPRINT"
        },
        {
            "name": "oompSize",
            "value": "eagle"
        },
        {
            "name": "oompColor",
            "value": "eagle-default"
        },
        {
            "name": "oompDesc",
            "value": "con-wago"
        },
        {
            "name": "oompIndex",
            "value": "233-236"
        },
        {
            "name": "oompName",
            "value": "eagle-default/con-wago/233-236"
        },
        {
            "name": "oompID",
            "value": "FOOTPRINT-eagle-eagle-default-con-wago-233-236"
        },
        {
            "name": "oompID",
            "value": "FOOTPRINT-eagle-eagle-default-con-wago-233-236"
        },
        {
            "name": "name",
            "value": ""
        }
    ]
}