{
    "tags": [
        {
            "name": "hexID",
            "value": "FZKCNRJRJ45OSTPJ128P8CXVERTICAL"
        },
        {
            "name": "oompType",
            "value": "FOOTPRINT"
        },
        {
            "name": "oompSize",
            "value": "kicad"
        },
        {
            "name": "oompColor",
            "value": "kicad-footprints"
        },
        {
            "name": "oompDesc",
            "value": "Connector_RJ"
        },
        {
            "name": "oompIndex",
            "value": "RJ45_OST_PJ012-8P8CX_Vertical"
        },
        {
            "name": "oompName",
            "value": "kicad-footprints/Connector_RJ/RJ45_OST_PJ012-8P8CX_Vertical"
        },
        {
            "name": "description",
            "value": "RJ45 vertical connector https://www.on-shore.com/wp-content/uploads/PJ012-8P8CX.pdf"
        },
        {
            "name": "tags",
            "value": "RJ45 PJ012"
        },
        {
            "name": "attribute",
            "value": "through_hole"
        },
        {
            "name": "3dmodel",
            "value": "${KICAD6_3DMODEL_DIR}/Connector_RJ.3dshapes/RJ45_OST_PJ012-8P8CX_Vertical.wrl"
        },
        {
            "name": "oompID",
            "value": "FOOTPRINT-kicad-kicad-footprints-Connector_RJ-RJ45_OST_PJ012-8P8CX_Vertical"
        },
        {
            "name": "oompID",
            "value": "FOOTPRINT-kicad-kicad-footprints-Connector_RJ-RJ45_OST_PJ012-8P8CX_Vertical"
        },
        {
            "name": "name",
            "value": ""
        }
    ]
}