{
    "tags": [
        {
            "name": "hexID",
            "value": "FZKRFCOILCRAFTMA5532AERFID"
        },
        {
            "name": "oompType",
            "value": "FOOTPRINT"
        },
        {
            "name": "oompSize",
            "value": "kicad"
        },
        {
            "name": "oompColor",
            "value": "kicad-footprints"
        },
        {
            "name": "oompDesc",
            "value": "RF_Antenna"
        },
        {
            "name": "oompIndex",
            "value": "Coilcraft_MA5532-AE_RFID"
        },
        {
            "name": "oompName",
            "value": "kicad-footprints/RF_Antenna/Coilcraft_MA5532-AE_RFID"
        },
        {
            "name": "description",
            "value": "RFID Transponder Coil"
        },
        {
            "name": "tags",
            "value": "antenna rfid coilcraft"
        },
        {
            "name": "attribute",
            "value": "smd"
        },
        {
            "name": "3dmodel",
            "value": "${KICAD6_3DMODEL_DIR}/RF_Antenna.3dshapes/Coilcraft_MA5532-AE_RFID.wrl"
        },
        {
            "name": "oompID",
            "value": "FOOTPRINT-kicad-kicad-footprints-RF_Antenna-Coilcraft_MA5532-AE_RFID"
        },
        {
            "name": "oompID",
            "value": "FOOTPRINT-kicad-kicad-footprints-RF_Antenna-Coilcraft_MA5532-AE_RFID"
        },
        {
            "name": "name",
            "value": ""
        }
    ]
}