{
    "tags": [
        {
            "name": "oompType",
            "value": "RESE"
        },
        {
            "name": "oompSize",
            "value": "0402"
        },
        {
            "name": "oompColor",
            "value": "X"
        },
        {
            "name": "oompDesc",
            "value": "O222"
        },
        {
            "name": "oompIndex",
            "value": "01"
        },
        {
            "name": "oplPartNumber",
            "value": {
                "code": "C-JLCC",
                "desc": "62.5mW Thick Film Resistors 50V ??100ppm/?? ??1% -55??~+155?? 2.2k?? 0402  Chip Resistor - Surface Mount ROHS",
                "name": "JLC Parts Library",
                "partID": "C25879"
            }
        },
        {
            "name": "distributorPartNumber",
            "value": {
                "code": "C-LCSC",
                "name": "LCSC",
                "partID": "C25879"
            }
        },
        {
            "name": "manufacturerPartNumber",
            "value": {
                "code": "C-XXXX",
                "name": "UNI-ROYAL(Uniroyal Elec)",
                "partID": "0402WGF2201TCE"
            }
        },
        {
            "name": "hexID",
            "value": "RESE-4O222-01"
        },
        {
            "name": "oompID",
            "value": "RESE-0402-X-O222-01"
        },
        {
            "name": "oompInstances",
            "value": {
                "ID": "R3",
                "PROJECT": "PROJ-SPAR-10615-STAN-01"
            }
        },
        {
            "name": "oompInstances",
            "value": {
                "ID": "R6",
                "PROJECT": "PROJ-SPAR-10615-STAN-01"
            }
        },
        {
            "name": "oompInstances",
            "value": {
                "ID": "R7",
                "PROJECT": "PROJ-SPAR-10615-STAN-01"
            }
        },
        {
            "name": "oompInstances",
            "value": {
                "ID": "R8",
                "PROJECT": "PROJ-SPAR-10615-STAN-01"
            }
        },
        {
            "name": "oompInstances",
            "value": {
                "ID": "R9",
                "PROJECT": "PROJ-SPAR-10615-STAN-01"
            }
        },
        {
            "name": "oompInstances",
            "value": {
                "ID": "R10",
                "PROJECT": "PROJ-SPAR-10615-STAN-01"
            }
        },
        {
            "name": "oompInstances",
            "value": {
                "ID": "R11",
                "PROJECT": "PROJ-SPAR-10615-STAN-01"
            }
        },
        {
            "name": "oompInstances",
            "value": {
                "ID": "R12",
                "PROJECT": "PROJ-SPAR-10615-STAN-01"
            }
        },
        {
            "name": "oompInstances",
            "value": {
                "ID": "R13",
                "PROJECT": "PROJ-SPAR-10615-STAN-01"
            }
        },
        {
            "name": "oompInstances",
            "value": {
                "ID": "R14",
                "PROJECT": "PROJ-SPAR-10615-STAN-01"
            }
        },
        {
            "name": "oompInstances",
            "value": {
                "ID": "R15",
                "PROJECT": "PROJ-SPAR-10615-STAN-01"
            }
        },
        {
            "name": "oompInstances",
            "value": {
                "ID": "R16",
                "PROJECT": "PROJ-SPAR-10615-STAN-01"
            }
        },
        {
            "name": "oompInstances",
            "value": {
                "ID": "R17",
                "PROJECT": "PROJ-SPAR-10615-STAN-01"
            }
        },
        {
            "name": "oompInstances",
            "value": {
                "ID": "R18",
                "PROJECT": "PROJ-SPAR-10615-STAN-01"
            }
        },
        {
            "name": "oompInstances",
            "value": {
                "ID": "R19",
                "PROJECT": "PROJ-SPAR-10615-STAN-01"
            }
        },
        {
            "name": "oompInstances",
            "value": {
                "ID": "R20",
                "PROJECT": "PROJ-SPAR-10615-STAN-01"
            }
        },
        {
            "name": "oompInstances",
            "value": {
                "ID": "R21",
                "PROJECT": "PROJ-SPAR-10615-STAN-01"
            }
        },
        {
            "name": "oompInstances",
            "value": {
                "ID": "R9",
                "PROJECT": "PROJ-SPAR-12081-STAN-01"
            }
        },
        {
            "name": "oompInstances",
            "value": {
                "ID": "R10",
                "PROJECT": "PROJ-SPAR-12081-STAN-01"
            }
        },
        {
            "name": "footprintKicad",
            "value": "FOOTPRINT-kicad-kicad-footprints-Resistor_SMD-R_0402_1005Metric"
        },
        {
            "name": "footprintKicad",
            "value": "FOOTPRINT-kicad-kicad-footprints-Resistor_SMD-R_0402_1005Metric_Pad0.72x0.64mm_HandSolder"
        },
        {
            "name": "symbolKicad",
            "value": "SYMBOL-kicad-kicad-symbols-Device-R"
        },
        {
            "name": "oompID",
            "value": "RESE-0402-X-O222-01"
        },
        {
            "name": "name",
            "value": "SMD (0402) 2.2k Ohm Resistor"
        }
    ]
}