{
    "tags": [
        {
            "name": "hexID",
            "value": "FZPGCEP125"
        },
        {
            "name": "oompType",
            "value": "FOOTPRINT"
        },
        {
            "name": "oompSize",
            "value": "eagle"
        },
        {
            "name": "oompColor",
            "value": "Pimoroni-Eagle-Library"
        },
        {
            "name": "oompDesc",
            "value": "gee_s"
        },
        {
            "name": "oompIndex",
            "value": "CEP125"
        },
        {
            "name": "oompName",
            "value": "Pimoroni-Eagle-Library/gee_s/CEP125"
        },
        {
            "name": "description",
            "value": "&lt;b&gt;POWER INDUCTORS&lt;/b&gt; (SMT Type)&lt;p&gt;\nSource: www.sumida.com/products/pdf/CEP125.pdf"
        },
        {
            "name": "oompID",
            "value": "FOOTPRINT-eagle-Pimoroni-Eagle-Library-gee_s-CEP125"
        },
        {
            "name": "oompID",
            "value": "FOOTPRINT-eagle-Pimoroni-Eagle-Library-gee_s-CEP125"
        },
        {
            "name": "name",
            "value": ""
        }
    ]
}