{
    "tags": [
        {
            "name": "hexID",
            "value": "FZKOB\\FIDFIDMODERNSILKSCREENTOP"
        },
        {
            "name": "oompType",
            "value": "FOOTPRINT"
        },
        {
            "name": "oompSize",
            "value": "kicad"
        },
        {
            "name": "oompColor",
            "value": "kicad-footprints"
        },
        {
            "name": "oompDesc",
            "value": "Obsolete\\Fiducial"
        },
        {
            "name": "oompIndex",
            "value": "Fiducial_Modern_SilkscreenTop"
        },
        {
            "name": "oompName",
            "value": "kicad-footprints/Obsolete\\Fiducial/Fiducial_Modern_SilkscreenTop"
        },
        {
            "name": "description",
            "value": "Fiducial, Modern, Silkscreen Top"
        },
        {
            "name": "attribute",
            "value": "smd"
        },
        {
            "name": "oompID",
            "value": "FOOTPRINT-kicad-kicad-footprints-Obsolete\\Fiducial-Fiducial_Modern_SilkscreenTop"
        },
        {
            "name": "oompID",
            "value": "FOOTPRINT-kicad-kicad-footprints-Obsolete\\Fiducial-Fiducial_Modern_SilkscreenTop"
        },
        {
            "name": "name",
            "value": ""
        }
    ]
}