{
    "tags": [
        {
            "name": "hexID",
            "value": "FZKTPTPPAD15X15"
        },
        {
            "name": "oompType",
            "value": "FOOTPRINT"
        },
        {
            "name": "oompSize",
            "value": "kicad"
        },
        {
            "name": "oompColor",
            "value": "kicad-footprints"
        },
        {
            "name": "oompDesc",
            "value": "TestPoint"
        },
        {
            "name": "oompIndex",
            "value": "TestPoint_Pad_1.5x1.5mm"
        },
        {
            "name": "oompName",
            "value": "kicad-footprints/TestPoint/TestPoint_Pad_1.5x1.5mm"
        },
        {
            "name": "description",
            "value": "SMD rectangular pad as test Point, square 1.5mm side length"
        },
        {
            "name": "tags",
            "value": "test point SMD pad rectangle square"
        },
        {
            "name": "attribute",
            "value": "exclude_from_pos_files exclude_from_bom"
        },
        {
            "name": "oompID",
            "value": "FOOTPRINT-kicad-kicad-footprints-TestPoint-TestPoint_Pad_1.5x1.5mm"
        },
        {
            "name": "oompID",
            "value": "FOOTPRINT-kicad-kicad-footprints-TestPoint-TestPoint_Pad_1.5x1.5mm"
        },
        {
            "name": "name",
            "value": ""
        }
    ]
}