{
    "tags": [
        {
            "name": "hexID",
            "value": "FZKCNJSTJSTPHDS24BPHDSS2X12P2HORIZONTAL"
        },
        {
            "name": "oompType",
            "value": "FOOTPRINT"
        },
        {
            "name": "oompSize",
            "value": "kicad"
        },
        {
            "name": "oompColor",
            "value": "kicad-footprints"
        },
        {
            "name": "oompDesc",
            "value": "Connector_JST"
        },
        {
            "name": "oompIndex",
            "value": "JST_PHD_S24B-PHDSS_2x12_P2.00mm_Horizontal"
        },
        {
            "name": "oompName",
            "value": "kicad-footprints/Connector_JST/JST_PHD_S24B-PHDSS_2x12_P2.00mm_Horizontal"
        },
        {
            "name": "description",
            "value": "JST PHD series connector, S24B-PHDSS (http://www.jst-mfg.com/product/pdf/eng/ePHD.pdf), generated with kicad-footprint-generator"
        },
        {
            "name": "tags",
            "value": "connector JST PHD horizontal"
        },
        {
            "name": "attribute",
            "value": "through_hole"
        },
        {
            "name": "3dmodel",
            "value": "${KICAD6_3DMODEL_DIR}/Connector_JST.3dshapes/JST_PHD_S24B-PHDSS_2x12_P2.00mm_Horizontal.wrl"
        },
        {
            "name": "oompID",
            "value": "FOOTPRINT-kicad-kicad-footprints-Connector_JST-JST_PHD_S24B-PHDSS_2x12_P2.00mm_Horizontal"
        },
        {
            "name": "oompID",
            "value": "FOOTPRINT-kicad-kicad-footprints-Connector_JST-JST_PHD_S24B-PHDSS_2x12_P2.00mm_Horizontal"
        },
        {
            "name": "name",
            "value": ""
        }
    ]
}