{
    "tags": [
        {
            "name": "hexID",
            "value": "FZKDD5WP58VERTICALKATHODEUP"
        },
        {
            "name": "oompType",
            "value": "FOOTPRINT"
        },
        {
            "name": "oompSize",
            "value": "kicad"
        },
        {
            "name": "oompColor",
            "value": "kicad-footprints"
        },
        {
            "name": "oompDesc",
            "value": "Diode_THT"
        },
        {
            "name": "oompIndex",
            "value": "D_5W_P5.08mm_Vertical_KathodeUp"
        },
        {
            "name": "oompName",
            "value": "kicad-footprints/Diode_THT/D_5W_P5.08mm_Vertical_KathodeUp"
        },
        {
            "name": "description",
            "value": "Diode, 5W series, Axial, Vertical, pin pitch=5.08mm, , length*diameter=8.9*3.7mm^2, , http://www.diodes.com/_files/packages/8686949.gif"
        },
        {
            "name": "tags",
            "value": "Diode 5W series Axial Vertical pin pitch 5.08mm  length 8.9mm diameter 3.7mm"
        },
        {
            "name": "attribute",
            "value": "through_hole"
        },
        {
            "name": "3dmodel",
            "value": "${KICAD6_3DMODEL_DIR}/Diode_THT.3dshapes/D_5W_P5.08mm_Vertical_KathodeUp.wrl"
        },
        {
            "name": "oompID",
            "value": "FOOTPRINT-kicad-kicad-footprints-Diode_THT-D_5W_P5.08mm_Vertical_KathodeUp"
        },
        {
            "name": "oompID",
            "value": "FOOTPRINT-kicad-kicad-footprints-Diode_THT-D_5W_P5.08mm_Vertical_KathodeUp"
        },
        {
            "name": "name",
            "value": ""
        }
    ]
}