{
    "tags": [
        {
            "name": "hexID",
            "value": "FZSRTFFC16"
        },
        {
            "name": "oompType",
            "value": "FOOTPRINT"
        },
        {
            "name": "oompSize",
            "value": "eagle"
        },
        {
            "name": "oompColor",
            "value": "SparkFun-Eagle-Libraries"
        },
        {
            "name": "oompDesc",
            "value": "SparkFun-Retired"
        },
        {
            "name": "oompIndex",
            "value": "FFC_16"
        },
        {
            "name": "oompName",
            "value": "SparkFun-Eagle-Libraries/SparkFun-Retired/FFC_16"
        },
        {
            "name": "oompID",
            "value": "FOOTPRINT-eagle-SparkFun-Eagle-Libraries-SparkFun-Retired-FFC_16"
        },
        {
            "name": "oompID",
            "value": "FOOTPRINT-eagle-SparkFun-Eagle-Libraries-SparkFun-Retired-FFC_16"
        },
        {
            "name": "name",
            "value": ""
        }
    ]
}