{
    "tags": [
        {
            "name": "hexID",
            "value": "FZEZETEXE2LINE"
        },
        {
            "name": "oompType",
            "value": "FOOTPRINT"
        },
        {
            "name": "oompSize",
            "value": "eagle"
        },
        {
            "name": "oompColor",
            "value": "eagle-default"
        },
        {
            "name": "oompDesc",
            "value": "zetex"
        },
        {
            "name": "oompIndex",
            "value": "E2LINE"
        },
        {
            "name": "oompName",
            "value": "eagle-default/zetex/E2LINE"
        },
        {
            "name": "oompID",
            "value": "FOOTPRINT-eagle-eagle-default-zetex-E2LINE"
        },
        {
            "name": "oompID",
            "value": "FOOTPRINT-eagle-eagle-default-zetex-E2LINE"
        },
        {
            "name": "name",
            "value": ""
        }
    ]
}