{
    "tags": [
        {
            "name": "hexID",
            "value": "HS6L"
        },
        {
            "name": "oompSort",
            "value": "0606L"
        },
        {
            "name": "oompType",
            "value": "HESH"
        },
        {
            "name": "oompSize",
            "value": "06"
        },
        {
            "name": "oompColor",
            "value": "L"
        },
        {
            "name": "oompDesc",
            "value": "STAN"
        },
        {
            "name": "oompIndex",
            "value": "01"
        },
        {
            "name": "oompVersion",
            "value": "27"
        },
        {
            "name": "ooShrinkRatio",
            "value": "2:1"
        },
        {
            "name": "oompClass",
            "value": "Wiring"
        },
        {
            "name": "oompClassCode",
            "value": "WIRE"
        },
        {
            "name": "oompID",
            "value": "HESH-06-L-STAN-01"
        },
        {
            "name": "name",
            "value": "6 mm Blue Heat Shrink"
        }
    ]
}