{
    "tags": [
        {
            "name": "hexID",
            "value": "FZPMECHANICALMTACT"
        },
        {
            "name": "oompType",
            "value": "FOOTPRINT"
        },
        {
            "name": "oompSize",
            "value": "eagle"
        },
        {
            "name": "oompColor",
            "value": "Pimoroni-Eagle-Library"
        },
        {
            "name": "oompDesc",
            "value": "pimoroni-mechanical"
        },
        {
            "name": "oompIndex",
            "value": "MINI_TACT"
        },
        {
            "name": "oompName",
            "value": "Pimoroni-Eagle-Library/pimoroni-mechanical/MINI_TACT"
        },
        {
            "name": "oompID",
            "value": "FOOTPRINT-eagle-Pimoroni-Eagle-Library-pimoroni-mechanical-MINI_TACT"
        },
        {
            "name": "oompID",
            "value": "FOOTPRINT-eagle-Pimoroni-Eagle-Library-pimoroni-mechanical-MINI_TACT"
        },
        {
            "name": "name",
            "value": ""
        }
    ]
}