{
    "tags": [
        {
            "name": "hexID",
            "value": "FZP1X5L"
        },
        {
            "name": "oompType",
            "value": "FOOTPRINT"
        },
        {
            "name": "oompSize",
            "value": "eagle"
        },
        {
            "name": "oompColor",
            "value": "Pimoroni-Eagle-Library"
        },
        {
            "name": "oompDesc",
            "value": "pimoroni"
        },
        {
            "name": "oompIndex",
            "value": "1X05_LONGPADS"
        },
        {
            "name": "oompName",
            "value": "Pimoroni-Eagle-Library/pimoroni/1X05_LONGPADS"
        },
        {
            "name": "oompID",
            "value": "FOOTPRINT-eagle-Pimoroni-Eagle-Library-pimoroni-1X05_LONGPADS"
        },
        {
            "name": "oompID",
            "value": "FOOTPRINT-eagle-Pimoroni-Eagle-Library-pimoroni-1X05_LONGPADS"
        },
        {
            "name": "name",
            "value": ""
        }
    ]
}