{
    "tags": [
        {
            "name": "hexID",
            "value": "FZPGL2825P"
        },
        {
            "name": "oompType",
            "value": "FOOTPRINT"
        },
        {
            "name": "oompSize",
            "value": "eagle"
        },
        {
            "name": "oompColor",
            "value": "Pimoroni-Eagle-Library"
        },
        {
            "name": "oompDesc",
            "value": "gee_s"
        },
        {
            "name": "oompIndex",
            "value": "L2825P"
        },
        {
            "name": "oompName",
            "value": "Pimoroni-Eagle-Library/gee_s/L2825P"
        },
        {
            "name": "description",
            "value": "&lt;b&gt;INDUCTOR&lt;/b&gt;&lt;p&gt;\nprecision wire wound"
        },
        {
            "name": "oompID",
            "value": "FOOTPRINT-eagle-Pimoroni-Eagle-Library-gee_s-L2825P"
        },
        {
            "name": "oompID",
            "value": "FOOTPRINT-eagle-Pimoroni-Eagle-Library-gee_s-L2825P"
        },
        {
            "name": "name",
            "value": ""
        }
    ]
}