{
    "tags": [
        {
            "name": "hexID",
            "value": "FZKPACKAGETOSOTSMTO54LONGPADWITHHOLEHOUSING"
        },
        {
            "name": "oompType",
            "value": "FOOTPRINT"
        },
        {
            "name": "oompSize",
            "value": "kicad"
        },
        {
            "name": "oompColor",
            "value": "kicad-footprints"
        },
        {
            "name": "oompDesc",
            "value": "Package_TO_SOT_SMD"
        },
        {
            "name": "oompIndex",
            "value": "TO-50-4_LongPad-WithHole_Housing"
        },
        {
            "name": "oompName",
            "value": "kicad-footprints/Package_TO_SOT_SMD/TO-50-4_LongPad-WithHole_Housing"
        },
        {
            "name": "description",
            "value": "TO-50-4 Macro X Package Style M238"
        },
        {
            "name": "tags",
            "value": "TO-50-4 Macro X Package Style M238"
        },
        {
            "name": "attribute",
            "value": "smd"
        },
        {
            "name": "3dmodel",
            "value": "${KICAD6_3DMODEL_DIR}/Package_TO_SOT_SMD.3dshapes/TO-50-4_LongPad-WithHole_Housing.wrl"
        },
        {
            "name": "oompID",
            "value": "FOOTPRINT-kicad-kicad-footprints-Package_TO_SOT_SMD-TO-50-4_LongPad-WithHole_Housing"
        },
        {
            "name": "oompID",
            "value": "FOOTPRINT-kicad-kicad-footprints-Package_TO_SOT_SMD-TO-50-4_LongPad-WithHole_Housing"
        },
        {
            "name": "name",
            "value": ""
        }
    ]
}