{
    "tags": [
        {
            "name": "hexID",
            "value": "FZSIPDIP8"
        },
        {
            "name": "oompType",
            "value": "FOOTPRINT"
        },
        {
            "name": "oompSize",
            "value": "eagle"
        },
        {
            "name": "oompColor",
            "value": "SparkFun-Eagle-Libraries"
        },
        {
            "name": "oompDesc",
            "value": "SparkFun-IC-Power"
        },
        {
            "name": "oompIndex",
            "value": "DIP-08"
        },
        {
            "name": "oompName",
            "value": "SparkFun-Eagle-Libraries/SparkFun-IC-Power/DIP-08"
        },
        {
            "name": "oompID",
            "value": "FOOTPRINT-eagle-SparkFun-Eagle-Libraries-SparkFun-IC-Power-DIP-08"
        },
        {
            "name": "oompID",
            "value": "FOOTPRINT-eagle-SparkFun-Eagle-Libraries-SparkFun-IC-Power-DIP-08"
        },
        {
            "name": "name",
            "value": ""
        }
    ]
}