{
    "tags": [
        {
            "name": "hexID",
            "value": "FZKTPTPTHTPADD1DRILL5"
        },
        {
            "name": "oompType",
            "value": "FOOTPRINT"
        },
        {
            "name": "oompSize",
            "value": "kicad"
        },
        {
            "name": "oompColor",
            "value": "kicad-footprints"
        },
        {
            "name": "oompDesc",
            "value": "TestPoint"
        },
        {
            "name": "oompIndex",
            "value": "TestPoint_THTPad_D1.0mm_Drill0.5mm"
        },
        {
            "name": "oompName",
            "value": "kicad-footprints/TestPoint/TestPoint_THTPad_D1.0mm_Drill0.5mm"
        },
        {
            "name": "description",
            "value": "THT pad as test Point, diameter 1.0mm, hole diameter 0.5mm"
        },
        {
            "name": "tags",
            "value": "test point THT pad"
        },
        {
            "name": "attribute",
            "value": "exclude_from_pos_files exclude_from_bom"
        },
        {
            "name": "oompID",
            "value": "FOOTPRINT-kicad-kicad-footprints-TestPoint-TestPoint_THTPad_D1.0mm_Drill0.5mm"
        },
        {
            "name": "oompID",
            "value": "FOOTPRINT-kicad-kicad-footprints-TestPoint-TestPoint_THTPad_D1.0mm_Drill0.5mm"
        },
        {
            "name": "name",
            "value": ""
        }
    ]
}