{
    "tags": [
        {
            "name": "hexID",
            "value": "HS3E"
        },
        {
            "name": "oompSort",
            "value": "0303E"
        },
        {
            "name": "oompType",
            "value": "HESH"
        },
        {
            "name": "oompSize",
            "value": "03"
        },
        {
            "name": "oompColor",
            "value": "E"
        },
        {
            "name": "oompDesc",
            "value": "STAN"
        },
        {
            "name": "oompIndex",
            "value": "01"
        },
        {
            "name": "oompVersion",
            "value": "27"
        },
        {
            "name": "ooShrinkRatio",
            "value": "2:1"
        },
        {
            "name": "oompClass",
            "value": "Wiring"
        },
        {
            "name": "oompClassCode",
            "value": "WIRE"
        },
        {
            "name": "oompID",
            "value": "HESH-03-E-STAN-01"
        },
        {
            "name": "name",
            "value": "3 mm Grey Heat Shrink"
        }
    ]
}