{
    "tags": [
        {
            "name": "hexID",
            "value": "FZKHOLHOL6PAD"
        },
        {
            "name": "oompType",
            "value": "FOOTPRINT"
        },
        {
            "name": "oompSize",
            "value": "kicad"
        },
        {
            "name": "oompColor",
            "value": "kicad-footprints"
        },
        {
            "name": "oompDesc",
            "value": "MountingHole"
        },
        {
            "name": "oompIndex",
            "value": "MountingHole_6mm_Pad"
        },
        {
            "name": "oompName",
            "value": "kicad-footprints/MountingHole/MountingHole_6mm_Pad"
        },
        {
            "name": "description",
            "value": "Mounting Hole 6mm"
        },
        {
            "name": "tags",
            "value": "mounting hole 6mm"
        },
        {
            "name": "attribute",
            "value": "exclude_from_pos_files exclude_from_bom"
        },
        {
            "name": "oompID",
            "value": "FOOTPRINT-kicad-kicad-footprints-MountingHole-MountingHole_6mm_Pad"
        },
        {
            "name": "oompID",
            "value": "FOOTPRINT-kicad-kicad-footprints-MountingHole-MountingHole_6mm_Pad"
        },
        {
            "name": "name",
            "value": ""
        }
    ]
}