{
    "tags": [
        {
            "name": "hexID",
            "value": "FZSSPARKFUNSENSSTC31"
        },
        {
            "name": "oompType",
            "value": "FOOTPRINT"
        },
        {
            "name": "oompSize",
            "value": "eagle"
        },
        {
            "name": "oompColor",
            "value": "SparkFun-Eagle-Libraries"
        },
        {
            "name": "oompDesc",
            "value": "SparkFun-Sensors"
        },
        {
            "name": "oompIndex",
            "value": "STC31"
        },
        {
            "name": "oompName",
            "value": "SparkFun-Eagle-Libraries/SparkFun-Sensors/STC31"
        },
        {
            "name": "oompID",
            "value": "FOOTPRINT-eagle-SparkFun-Eagle-Libraries-SparkFun-Sensors-STC31"
        },
        {
            "name": "oompID",
            "value": "FOOTPRINT-eagle-SparkFun-Eagle-Libraries-SparkFun-Sensors-STC31"
        },
        {
            "name": "name",
            "value": ""
        }
    ]
}